{"is_source_file": false, "format": "", "description": "", "external_files": [], "external_methods": [], "published": [], "classes": [], "methods": [], "calls": [], "search-terms": [], "state": 2, "file_id": 1, "knowledge_revision": 24, "git_revision": "5e987d97916239370dee60e4d47d15ba6defa6b1", "hash": "4e124ca9ed5cde749a74c8139f909fc4", "format-version": 4, "code-base-name": "tic_tac_toe_frontend", "filename": "README.md", "revision_history": [{"24": "5e987d97916239370dee60e4d47d15ba6defa6b1"}]}